detectgibberish/__init__.py
detectgibberish/gibberish.py
detectgibberish/keyboard.py
detectgibberish/version.py
detectgibberish-1.0.3.dist-info/LICENSE
detectgibberish-1.0.3.dist-info/METADATA
detectgibberish-1.0.3.dist-info/WHEEL
detectgibberish-1.0.3.dist-info/top_level.txt
detectgibberish-1.0.3.dist-info/RECORD
