Metadata-Version: 2.1
Name: detectgibberish
Version: 1.0.3
Summary: Python Package to detect gibberish word
Home-page: https://github.com/sandeepeecs/detect-gibberish
Author: Sandeep Reddy
Author-email: poga.sandeep@gmail.com
License: MIT License
Keywords: gibberish word
Platform: UNKNOWN
Classifier: Topic :: Text Processing :: General
Requires-Dist: pytest
Requires-Dist: pytest-cov
